pytron/__init__.py
pytron/application.py
pytron/bindings.py
pytron/chromewebview.py
pytron/cli.py
pytron/console.py
pytron/core.py
pytron/exceptions.py
pytron/inspector.py
pytron/inspector_ui.py
pytron/llms.md
pytron/menu.py
pytron/nsis-setup.exe
pytron/plugin.py
pytron/router.py
pytron/serializer.py
pytron/shortcuts.py
pytron/state.py
pytron/tray.py
pytron/updater.py
pytron/utf8_hook.py
pytron/utils.py
pytron/webview.py
pytron/apputils/__init__.py
pytron/apputils/chrome_ipc.py
pytron/apputils/codegen.py
pytron/apputils/config.py
pytron/apputils/deadmansswitch.py
pytron/apputils/extras.py
pytron/apputils/native.py
pytron/apputils/shell.py
pytron/apputils/windows.py
pytron/commands/__init__.py
pytron/commands/android.py
pytron/commands/build.py
pytron/commands/doctor.py
pytron/commands/engine.py
pytron/commands/frontend.py
pytron/commands/harvest.py
pytron/commands/helpers.py
pytron/commands/info.py
pytron/commands/init.py
pytron/commands/install.py
pytron/commands/login.py
pytron/commands/package.py
pytron/commands/plugin.py
pytron/commands/run.py
pytron/commands/show.py
pytron/commands/uninstall.py
pytron/commands/workflow.py
pytron/dependancies/WebView2Loader.dll
pytron/dependancies/libwebview.so
pytron/dependancies/libwebview_arm64.dylib
pytron/dependancies/libwebview_x64.dylib
pytron/dependancies/webview.dll
pytron/engines/chrome/adapter.py
pytron/engines/chrome/engine.py
pytron/engines/chrome/forge.py
pytron/engines/chrome/shell/package.json
pytron/engines/chrome/shell/preload.js
pytron/engines/chrome/shell/shell.js
pytron/installer/Installation.nsi
pytron/installer/header.bmp
pytron/installer/pytron.ico
pytron/installer/sidebar.bmp
pytron/manifests/README.md
pytron/manifests/windows-utf8.manifest
pytron/pack/__init__.py
pytron/pack/assets.py
pytron/pack/installers.py
pytron/pack/nuitka.py
pytron/pack/pyinstaller.py
pytron/pack/secure.py
pytron/pack/utils.py
pytron/pack/secure_loader/icon.ico
pytron/platforms/__init__.py
pytron/platforms/darwin.py
pytron_kit-0.3.5.dist-info/licenses/LICENSE
pytron_kit-0.3.5.dist-info/METADATA
pytron_kit-0.3.5.dist-info/WHEEL
pytron_kit-0.3.5.dist-info/entry_points.txt
pytron_kit-0.3.5.dist-info/top_level.txt
pytron_kit-0.3.5.dist-info/RECORD
