Metadata-Version: 2.4
Name: pytron-kit
Version: 0.3.5
Summary: An Electron-like library for Python to build Cross Platform Apps
Author: Ghua8088
License: Apache-2.0
Keywords: electron,app,desktop,android,webview
Classifier: Programming Language :: Python :: 3
Classifier: License :: OSI Approved :: Apache Software License
Classifier: Operating System :: OS Independent
Requires-Python: >=3.7
License-File: LICENSE
Requires-Dist: watchfiles
Requires-Dist: pydantic
Requires-Dist: importlib-metadata; python_version < "3.8"
Requires-Dist: pyinstaller
Requires-Dist: Pillow
Requires-Dist: pyobjc-framework-Cocoa; sys_platform == "darwin"
Requires-Dist: pyobjc-framework-WebKit; sys_platform == "darwin"
Requires-Dist: PyGObject==3.54.5; sys_platform == "linux"
Requires-Dist: rich
Requires-Dist: lief
Requires-Dist: nuitka
Requires-Dist: zstandard
Requires-Dist: comtypes; sys_platform == "win32"
Requires-Dist: cryptography
Requires-Dist: keyring
Requires-Dist: requests
Dynamic: license-file
